openapiipify/__init__.py
openapiipify/api_client.py
openapiipify/api_response.py
openapiipify/configuration.py
openapiipify/exceptions.py
openapiipify/py.typed
openapiipify/rest.py
openapiipify/api/__init__.py
openapiipify/api/default_api.py
openapiipify/models/__init__.py
openapiipify/models/get_ip200_response.py
openapiipify-6.0.0.dist-info/METADATA
openapiipify-6.0.0.dist-info/WHEEL
openapiipify-6.0.0.dist-info/top_level.txt
openapiipify-6.0.0.dist-info/RECORD
